{
  "project_info": {
    "project_number": "39299714410",
    "firebase_url": "https://contacts-app-7f3a0-default-rtdb.firebaseio.com",
    "project_id": "contacts-app-7f3a0",
    "storage_bucket": "contacts-app-7f3a0.appspot.com"
  },
  "client": [
    {
      "client_info": {
        "mobilesdk_app_id": "1:39299714410:android:2d083e1856e8621282e913",
        "android_client_info": {
          "package_name": "com.example.week6taskcontactapp"
        }
      },
      "oauth_client": [
        {
          "client_id": "39299714410-qujhak6egikqmon602be003qjbvvfe3r.apps.googleusercontent.com",
          "client_type": 3
        }
      ],
      "api_key": [
        {
          "current_key": "AIzaSyDA8rximfuLy0X3DzB73NoUgNbbsYbwNz8"
        }
      ],
      "services": {
        "appinvite_service": {
          "other_platform_oauth_client": [
            {
              "client_id": "39299714410-qujhak6egikqmon602be003qjbvvfe3r.apps.googleusercontent.com",
              "client_type": 3
            }
          ]
        }
      }
    },
    {
      "client_info": {
        "mobilesdk_app_id": "1:39299714410:android:bb2e6e5a7d00458c82e913",
        "android_client_info": {
          "package_name": "com.wiseman.paul.contactapp"
        }
      },
      "oauth_client": [
        {
          "client_id": "39299714410-qujhak6egikqmon602be003qjbvvfe3r.apps.googleusercontent.com",
          "client_type": 3
        }
      ],
      "api_key": [
        {
          "current_key": "AIzaSyDA8rximfuLy0X3DzB73NoUgNbbsYbwNz8"
        }
      ],
      "services": {
        "appinvite_service": {
          "other_platform_oauth_client": [
            {
              "client_id": "39299714410-qujhak6egikqmon602be003qjbvvfe3r.apps.googleusercontent.com",
              "client_type": 3
            }
          ]
        }
      }
    },
    {
      "client_info": {
        "mobilesdk_app_id": "1:39299714410:android:e01164d91c6bb49082e913",
        "android_client_info": {
          "package_name": "com.wiseman.paul.contactappweek6"
        }
      },
      "oauth_client": [
        {
          "client_id": "39299714410-qujhak6egikqmon602be003qjbvvfe3r.apps.googleusercontent.com",
          "client_type": 3
        }
      ],
      "api_key": [
        {
          "current_key": "AIzaSyDA8rximfuLy0X3DzB73NoUgNbbsYbwNz8"
        }
      ],
      "services": {
        "appinvite_service": {
          "other_platform_oauth_client": [
            {
              "client_id": "39299714410-qujhak6egikqmon602be003qjbvvfe3r.apps.googleusercontent.com",
              "client_type": 3
            }
          ]
        }
      }
    },
    {
      "client_info": {
        "mobilesdk_app_id": "1:39299714410:android:85e3744c08d4f8b782e913",
        "android_client_info": {
          "package_name": "ng.com.jedun.continousintegrationproject"
        }
      },
      "oauth_client": [
        {
          "client_id": "39299714410-qujhak6egikqmon602be003qjbvvfe3r.apps.googleusercontent.com",
          "client_type": 3
        }
      ],
      "api_key": [
        {
          "current_key": "AIzaSyDA8rximfuLy0X3DzB73NoUgNbbsYbwNz8"
        }
      ],
      "services": {
        "appinvite_service": {
          "other_platform_oauth_client": [
            {
              "client_id": "39299714410-qujhak6egikqmon602be003qjbvvfe3r.apps.googleusercontent.com",
              "client_type": 3
            }
          ]
        }
      }
    }
  ],
  "configuration_version": "1"
}